{"node": {"0209519333bbdc1e779c12ef3b0292d4": ["Map", {"vx": {"attribute_type": "INPUT", "data_type": "STRINPUT", "user_data": {"value": 0.0}}, "vy": {"attribute_type": "INPUT", "data_type": "STRINPUT", "user_data": {"value": 0.0}}, "alphax": {"attribute_type": "INPUT", "data_type": "STRINPUT", "user_data": {"value": -0.0}}, "original_upper": {"attribute_type": "CONFIG", "data_type": "STRINPUT", "user_data": {"value": "1"}}, "original_lower": {"attribute_type": "CONFIG", "data_type": "STRINPUT", "user_data": {"value": -1}}, "upper": {"attribute_type": "CONFIG", "data_type": "STRINPUT", "user_data": {"value": "20"}}, "lower": {"attribute_type": "CONFIG", "data_type": "STRINPUT", "user_data": {"value": "-20"}}, "mapped_value": {"attribute_type": "OUTPUT", "data_type": "STRINPUT", "user_data": {"value": [0.0, 0.0, -0.0]}}, "pos": {"attribute_type": "CONFIG", "data_type": "CONFIG", "user_data": {"value": [232, 584]}}}], "5c98fa9819da2edda0212a7bf5775118": ["Publisher", {"name": {"attribute_type": "INPUT", "data_type": "STRINPUT", "user_data": {"value": "MOTOR_CONTROL"}}, "msg_name": {"attribute_type": "INPUT", "data_type": "STRINPUT", "user_data": {"value": "RPM"}}, "msg_type": {"attribute_type": "INPUT", "data_type": "STRINPUT", "user_data": {"value": "list"}}, "frequency": {"attribute_type": "INPUT", "data_type": "STRINPUT", "user_data": {"value": "0.01"}}, "msg": {"attribute_type": "INPUT", "data_type": "STRINPUT", "user_data": {"value": [0.0, 0.0, -0.0]}}, "pos": {"attribute_type": "CONFIG", "data_type": "CONFIG", "user_data": {"value": [808, 524]}}}], "96d43df1133437b7e7182002299644e0": ["Subscriber", {"puuid": {"attribute_type": "INPUT", "data_type": "STRINPUT", "user_data": {"value": "TBotVizer"}}, "name": {"attribute_type": "INPUT", "data_type": "STRINPUT", "user_data": {"value": "MOTOR_CONTROL"}}, "msg_name": {"attribute_type": "INPUT", "data_type": "STRINPUT", "user_data": {"value": "RPM"}}, "msg": {"attribute_type": "OUTPUT", "data_type": "MULTILINEINPUT", "user_data": {"value": [0.0, 0.0, -0.0]}}, "pos": {"attribute_type": "CONFIG", "data_type": "CONFIG", "user_data": {"value": [435, 51]}}}]}, "link": [["0209519333bbdc1e779c12ef3b0292d4", "vx", "0209519333bbdc1e779c12ef3b0292d4", "vx"], ["0209519333bbdc1e779c12ef3b0292d4", "vy", "0209519333bbdc1e779c12ef3b0292d4", "vy"], ["0209519333bbdc1e779c12ef3b0292d4", "alphax", "0209519333bbdc1e779c12ef3b0292d4", "alphax"], ["0209519333bbdc1e779c12ef3b0292d4", "vx", "0209519333bbdc1e779c12ef3b0292d4", "vx"], ["0209519333bbdc1e779c12ef3b0292d4", "vy", "0209519333bbdc1e779c12ef3b0292d4", "vy"], ["0209519333bbdc1e779c12ef3b0292d4", "alphax", "0209519333bbdc1e779c12ef3b0292d4", "alphax"], ["0209519333bbdc1e779c12ef3b0292d4", "vx", "0209519333bbdc1e779c12ef3b0292d4", "vx"], ["0209519333bbdc1e779c12ef3b0292d4", "vy", "0209519333bbdc1e779c12ef3b0292d4", "vy"], ["0209519333bbdc1e779c12ef3b0292d4", "alphax", "0209519333bbdc1e779c12ef3b0292d4", "alphax"], ["0209519333bbdc1e779c12ef3b0292d4", "mapped_value", "5c98fa9819da2edda0212a7bf5775118", "msg"]]}